Verilog/S1-T5-behavioural.v
// S1-T5 (DDS-mini-project-2024-25)
// Dineflow - Smart Automatic Restaurant Management System
// Team members-
// 1) Rakshith Ashok Kumar - 231CS147
// 2) Utsav Singh Bhamra - 231CS161
// 3) Akshaj PVY - 231CS109


module restaurant_management_system (
     input clk,
     input reset,
     input [1:0] table0_order_item, // 2-bit order items
     input table0_order_valid,
     input [1:0] table1_order_item, // 2-bit order items
     input table1_order_valid,
     output reg [7:0] table0_bill,
     output reg [7:0] table1_bill,
     output reg table0_order_reject,
     output reg table1_order_reject,
     output reg [3:0] table0_queue_size,
     output reg [3:0] table1_queue_size,
     output reg [1:0] table0_ready_item, // 2-bit ready items
     output reg [1:0] table1_ready_item, // 2-bit ready items
     output reg table0_item_ready,
     output reg table1_item_ready
 );

   // Parameters
   parameter NUM_ITEMS = 4; // Items 0 to 3
   parameter QUEUE_SIZE = 16;

   // Inventory
   reg [3:0] inventory [0:NUM_ITEMS-1];

   // Menu prices and preparation times
   reg [7:0] item_prices [0:NUM_ITEMS-1];
   reg [7:0] item_prep_times [0:NUM_ITEMS-1];

   // Order queues
   reg [1:0] table0_queue [0:QUEUE_SIZE-1]; // 2-bit order items
   reg [1:0] table1_queue [0:QUEUE_SIZE-1]; // 2-bit order items
   reg [3:0] table0_queue_head, table0_queue_tail;
   reg [3:0] table1_queue_head, table1_queue_tail;

   // Timers
   reg [7:0] table0_timer, table1_timer;

   integer i;

   // Initialize inventory, prices, and prep times
   initial begin
       for (i = 0; i < NUM_ITEMS; i = i + 1) begin
           inventory[i] = 5;
           item_prices[i] = i+2; // Prices set to 0,1,2,3
           item_prep_times[i] = i+1; // Preparation times set to 0,1,2,3
       end
   end

   always @(posedge clk or posedge reset) begin
       if (reset) begin
           // Reset all registers
           table0_bill <= 0;
           table1_bill <= 0;
           table0_order_reject <= 0;
           table1_order_reject <= 0;
           table0_queue_size <= 0;
           table1_queue_size <= 0;
           table0_ready_item <= 0;
           table1_ready_item <= 0;
           table0_item_ready <= 0;
           table1_item_ready <= 0;
           table0_queue_head <= 0;
           table0_queue_tail <= 0;
           table1_queue_head <= 0;
           table1_queue_tail <= 0;
           table0_timer <= 0;
           table1_timer <= 0;

           for (i = 0; i < NUM_ITEMS; i = i + 1) begin
               inventory[i] <= 5;
           end
       end else begin
           // Handle orders for Table 0
           if (table0_order_valid) begin
               if (inventory[table0_order_item] > 0 && table0_queue_size < QUEUE_SIZE) begin
                   inventory[table0_order_item] <= inventory[table0_order_item] - 1;
                   table0_queue[table0_queue_tail] <= table0_order_item;
                   table0_queue_tail <= (table0_queue_tail + 1) % QUEUE_SIZE;
                   table0_queue_size <= table0_queue_size + 1;
                   table0_bill <= table0_bill + item_prices[table0_order_item];
                   table0_order_reject <= 0;
               end else begin
                   table0_order_reject <= 1;
               end
           end else begin
               table0_order_reject <= 0;
           end

           // Handle orders for Table 1
           if (table1_order_valid) begin
               if (inventory[table1_order_item] > 0 && table1_queue_size < QUEUE_SIZE) begin
                   inventory[table1_order_item] <= inventory[table1_order_item] - 1;
                   table1_queue[table1_queue_tail] <= table1_order_item;
                   table1_queue_tail <= (table1_queue_tail + 1) % QUEUE_SIZE;
                   table1_queue_size <= table1_queue_size + 1;
                   table1_bill <= table1_bill + item_prices[table1_order_item];
                   table1_order_reject <= 0;
               end else begin
                   table1_order_reject <= 1;
               end
           end else begin
               table1_order_reject <= 0;
           end

           // Handle timers and item readiness for Table 0
           if (table0_queue_size > 0) begin
               if (table0_timer == 0) begin
                   table0_timer <= item_prep_times[table0_queue[table0_queue_head]];
               end else if (table0_timer == 1) begin
                   table0_ready_item <= table0_queue[table0_queue_head];
                   table0_item_ready <= 1;
                   table0_queue_head <= (table0_queue_head + 1) % QUEUE_SIZE;
                   table0_queue_size <= table0_queue_size - 1;
                   table0_timer <= 0;
               end else begin
                   table0_timer <= table0_timer - 1;
                   table0_item_ready <= 0;
               end
           end else begin
               table0_item_ready <= 0;
           end

           // Handle timers and item readiness for Table 1
           if (table1_queue_size > 0) begin
               if (table1_timer == 0) begin
                   table1_timer <= item_prep_times[table1_queue[table1_queue_head]];
               end else if (table1_timer == 1) begin
                   table1_ready_item <= table1_queue[table1_queue_head];
                   table1_item_ready <= 1;
                   table1_queue_head <= (table1_queue_head + 1) % QUEUE_SIZE;
                   table1_queue_size <= table1_queue_size - 1;
                   table1_timer <= 0;
               end else begin
                   table1_timer <= table1_timer - 1;
                   table1_item_ready <= 0;
               end
           end else begin
               table1_item_ready <= 0;
           end
       end
   end

endmodule

Verilog/S1-T5-tb.v
module restaurant_management_system_tb;

    // Inputs
    reg clk;
    reg reset;
    reg [1:0] table0_order_item; // 2-bit order items
    reg table0_order_valid;
    reg [1:0] table1_order_item; // 2-bit order items
    reg table1_order_valid;

    // Outputs
    wire [7:0] table0_bill;
    wire [7:0] table1_bill;
    wire table0_order_reject;
    wire table1_order_reject;
    wire [3:0] table0_queue_size;
    wire [3:0] table1_queue_size;
    wire [1:0] table0_ready_item; // 2-bit ready items
    wire [1:0] table1_ready_item; // 2-bit ready items
    wire table0_item_ready;
    wire table1_item_ready;

    // Instantiate the Unit Under Test (UUT)
    restaurant_management_system uut (
        .clk(clk), 
        .reset(reset), 
        .table0_order_item(table0_order_item), 
        .table0_order_valid(table0_order_valid), 
        .table1_order_item(table1_order_item), 
        .table1_order_valid(table1_order_valid), 
        .table0_bill(table0_bill), 
        .table1_bill(table1_bill), 
        .table0_order_reject(table0_order_reject), 
        .table1_order_reject(table1_order_reject), 
        .table0_queue_size(table0_queue_size), 
        .table1_queue_size(table1_queue_size), 
        .table0_ready_item(table0_ready_item), 
        .table1_ready_item(table1_ready_item), 
        .table0_item_ready(table0_item_ready), 
        .table1_item_ready(table1_item_ready)
    );

    // Clock generation
    initial begin
        clk = 0;
        forever #5 clk = ~clk; // 10 time units period
    end

    initial begin 
        $dumpfile("S1-T5.vcd");
        $dumpvars(0,restaurant_management_system_tb);
    end

    // Test procedure
    initial begin
        // Initialize Inputs
        reset = 1;
        table0_order_item = 0;
        table0_order_valid = 0;
        table1_order_item = 0;
        table1_order_valid = 0;

        // Wait 100 ns for global reset to finish
        #100;
        reset = 0;

        // Test Case 1: Table 0 orders item 2
        #10 table0_order_item = 2;
        #10 table0_order_valid = 1;
        #10 table0_order_valid = 0;
        $display("Time=%t | Table 0 Ordered Item: %d", $time, table0_order_item);
        if (!table0_order_reject) begin
            $display("Time=%t | Updated Bill for Table 0: %d", $time, table0_bill);
        end else begin
            $display("Time=%t | Table 0 Order Rejected (Inventory or Queue Full)", $time);
        end

        // Test Case 2: Table 1 orders item 3
        #20 table1_order_item = 3;
        #10 table1_order_valid = 1;
        #10 table1_order_valid = 0;
        $display("Time=%t | Table 1 Ordered Item: %d", $time, table1_order_item);
        if (!table1_order_reject) begin
            $display("Time=%t | Updated Bill for Table 1: %d", $time, table1_bill);
        end else begin
            $display("Time=%t | Table 1 Order Rejected (Inventory or Queue Full)", $time);
        end

        // Test Case 3: Table 0 orders item 2 again
        #20 table0_order_item = 2;
        #10 table0_order_valid = 1;
        #10 table0_order_valid = 0;
        $display("Time=%t | Table 0 Ordered Item: %d", $time, table0_order_item);
        if (!table0_order_reject) begin
            $display("Time=%t | Updated Bill for Table 0: %d", $time, table0_bill);
        end else begin
            $display("Time=%t | Table 0 Order Rejected (Inventory or Queue Full)", $time);
        end

        // Test Case 4: Table 1 orders items 1, 2, 3 repeatedly (total 6 orders)
        repeat (6) begin
            #20 table1_order_item = ($random % 3) + 1; // Select item 1, 2, or 3
            #10 table1_order_valid = 1;
            #10 table1_order_valid = 0;
            $display("Time=%t | Table 1 Ordered Item: %d", $time, table1_order_item);
            if (!table1_order_reject) begin
                $display("Time=%t | Updated Bill for Table 1: %d", $time, table1_bill);
            end else begin
                $display("Time=%t | Table 1 Order Rejected (Inventory or Queue Full)", $time);
            end
        end

        // Wait for items to be ready
        #500;

        // Test Case 5: Table 0 orders multiple items to fill queue
        repeat (16) begin
            #20 table0_order_item = ($random % 3) + 1; // Select item 1, 2, or 3
            #10 table0_order_valid = 1;
            #10 table0_order_valid = 0;
            $display("Time=%t | Table 0 Ordered Item: %d", $time, table0_order_item);
            if (!table0_order_reject) begin
                $display("Time=%t | Updated Bill for Table 0: %d", $time, table0_bill);
            end else begin
                $display("Time=%t | Table 0 Order Rejected (Inventory or Queue Full)", $time);
            end
        end

        // Test Case 6: Table 0 tries to order when queue is full (should be rejected)
        #20 table0_order_item = 1;
        #10 table0_order_valid = 1;
        #10 table0_order_valid = 0;
        $display("Time=%t | Table 0 Ordered Item: %d", $time, table0_order_item);
        if (table0_order_reject) begin
            $display("Time=%t | Table 0 Order Rejected (Queue Full)", $time);
        end else begin
            $display("Time=%t | Updated Bill for Table 0: %d", $time, table0_bill);
        end

        // Wait for simulation to finish
        #1000;

        // Capture the final bills
        $display("\n================== Final Results ==================");
        $display("Final Bill for Table 0: %d", table0_bill);
        $display("Final Bill for Table 1: %d", table1_bill);
        $display("Total Simulation Time: %t units", $time);
        $display("==================================================\n");

        $finish;
    end

endmodule

Verilog/S1-T5.vcd
$date
	Thu Oct 17 14:18:53 2024
$end
$version
	Icarus Verilog
$end
$timescale
	1s
$end
$scope module restaurant_management_system_tb $end
$var wire 2 ! table1_ready_item [1:0] $end
$var wire 4 " table1_queue_size [3:0] $end
$var wire 1 # table1_order_reject $end
$var wire 1 $ table1_item_ready $end
$var wire 8 % table1_bill [7:0] $end
$var wire 2 & table0_ready_item [1:0] $end
$var wire 4 ' table0_queue_size [3:0] $end
$var wire 1 ( table0_order_reject $end
$var wire 1 ) table0_item_ready $end
$var wire 8 * table0_bill [7:0] $end
$var reg 1 + clk $end
$var reg 1 , reset $end
$var reg 2 - table0_order_item [1:0] $end
$var reg 1 . table0_order_valid $end
$var reg 2 / table1_order_item [1:0] $end
$var reg 1 0 table1_order_valid $end
$scope module uut $end
$var wire 1 + clk $end
$var wire 1 , reset $end
$var wire 2 1 table0_order_item [1:0] $end
$var wire 1 . table0_order_valid $end
$var wire 2 2 table1_order_item [1:0] $end
$var wire 1 0 table1_order_valid $end
$var reg 8 3 table0_bill [7:0] $end
$var reg 1 ) table0_item_ready $end
$var reg 1 ( table0_order_reject $end
$var reg 4 4 table0_queue_head [3:0] $end
$var reg 4 5 table0_queue_size [3:0] $end
$var reg 4 6 table0_queue_tail [3:0] $end
$var reg 2 7 table0_ready_item [1:0] $end
$var reg 8 8 table0_timer [7:0] $end
$var reg 8 9 table1_bill [7:0] $end
$var reg 1 $ table1_item_ready $end
$var reg 1 # table1_order_reject $end
$var reg 4 : table1_queue_head [3:0] $end
$var reg 4 ; table1_queue_size [3:0] $end
$var reg 4 < table1_queue_tail [3:0] $end
$var reg 2 = table1_ready_item [1:0] $end
$var reg 8 > table1_timer [7:0] $end
$var integer 32 ? i [31:0] $end
$upscope $end
$upscope $end
$enddefinitions $end
#0
$dumpvars
b100 ?
b0 >
b0 =
b0 <
b0 ;
b0 :
b0 9
b0 8
b0 7
b0 6
b0 5
b0 4
b0 3
b0 2
b0 1
00
b0 /
0.
b0 -
1,
0+
b0 *
0)
0(
b0 '
b0 &
b0 %
0$
0#
b0 "
b0 !
$end
#5
b100 ?
1+
#10
0+
#15
b100 ?
1+
#20
0+
#25
b100 ?
1+
#30
0+
#35
b100 ?
1+
#40
0+
#45
b100 ?
1+
#50
0+
#55
b100 ?
1+
#60
0+
#65
b100 ?
1+
#70
0+
#75
b100 ?
1+
#80
0+
#85
b100 ?
1+
#90
0+
#95
b100 ?
1+
#100
0+
0,
#105
1+
#110
0+
b10 -
b10 1
#115
1+
#120
0+
1.
#125
b100 *
b100 3
b1 '
b1 5
b1 6
1+
#130
0+
0.
#135
b11 8
1+
#140
0+
#145
b10 8
1+
#150
0+
b11 /
b11 2
#155
b1 8
1+
#160
0+
10
#165
b0 8
b0 '
b0 5
b1 4
1)
b10 &
b10 7
b101 %
b101 9
b1 "
b1 ;
b1 <
1+
#170
0+
00
#175
b100 >
0)
1+
#180
0+
#185
b11 >
1+
#190
0+
#195
b10 >
1+
#200
0+
1.
#205
b1 >
b1000 *
b1000 3
b1 '
b1 5
b10 6
1+
#210
0+
0.
#215
b0 >
b0 "
b0 ;
b1 :
1$
b11 !
b11 =
b11 8
1+
#220
0+
#225
0$
b10 8
1+
#230
0+
#235
b1 8
1+
#240
0+
10
#245
b0 8
b0 '
b0 5
b10 4
1)
b1010 %
b1010 9
b1 "
b1 ;
b10 <
1+
#250
0+
00
#255
b100 >
0)
1+
#260
0+
#265
b11 >
1+
#270
0+
b0 /
b0 2
#275
b10 >
1+
#280
0+
10
#285
b1 >
b1100 %
b1100 9
b10 "
b10 ;
b11 <
1+
#290
0+
00
#295
b0 >
b1 "
b1 ;
b10 :
1$
1+
#300
0+
#305
b1 >
1+
#310
0+
b1 /
b1 2
#315
b0 >
b0 "
b0 ;
b11 :
b0 !
b0 =
1+
#320
0+
10
#325
0$
b1111 %
b1111 9
b1 "
b1 ;
b100 <
1+
#330
0+
00
#335
b10 >
1+
#340
0+
#345
b1 >
1+
#350
0+
b11 /
b11 2
#355
b0 >
b0 "
b0 ;
b100 :
1$
b1 !
b1 =
1+
#360
0+
10
#365
0$
b10100 %
b10100 9
b1 "
b1 ;
b101 <
1+
#370
0+
00
#375
b100 >
1+
#380
0+
#385
b11 >
1+
#390
0+
b1 /
b1 2
#395
b10 >
1+
#400
0+
10
#405
b1 >
b10111 %
b10111 9
b10 "
b10 ;
b110 <
1+
#410
0+
00
#415
b0 >
b1 "
b1 ;
b101 :
1$
b11 !
b11 =
1+
#420
0+
#425
b10 >
1+
#430
0+
b11 /
b11 2
#435
0$
b1 >
1+
#440
0+
10
#445
b0 >
b110 :
1$
b1 !
b1 =
b11100 %
b11100 9
b0 "
b0 ;
b111 <
1+
#450
0+
00
#455
0$
1+
